mcp_server_solotodo/__init__.py
mcp_server_solotodo/mappings.py
mcp_server_solotodo/mcp.py
mcp_server_solotodo/schemas.py
mcp_server_solotodo/solotodo.py
mcp_server_solotodo/utils.py
mcp_server_solotodo-1.0.0.dist-info/METADATA
mcp_server_solotodo-1.0.0.dist-info/WHEEL
mcp_server_solotodo-1.0.0.dist-info/entry_points.txt
mcp_server_solotodo-1.0.0.dist-info/RECORD
