Metadata-Version: 2.4
Name: mcp-server-solotodo
Version: 1.0.0
Summary: MCP server for searching laptops on SoloTodo.cl
Requires-Python: >=3.12
Requires-Dist: mcp[cli]>=1.10.1
Requires-Dist: requests>=2.32.4
